<?xml version="1.0" encoding="UTF-8"?>
<GenRun Id="synth_1" LaunchPart="xc7a100tcsg324-1" LaunchTime="1779093767">
  <File Type="PA-TCL" Name="top_gsplat.tcl"/>
  <File Type="RDS-PROPCONSTRS" Name="top_gsplat_drc_synth.rpt"/>
  <File Type="REPORTS-TCL" Name="top_gsplat_reports.tcl"/>
  <File Type="RDS-RDS" Name="top_gsplat.vds"/>
  <File Type="RDS-UTIL" Name="top_gsplat_utilization_synth.rpt"/>
  <File Type="RDS-UTIL-PB" Name="top_gsplat_utilization_synth.pb"/>
  <File Type="RDS-DCP" Name="top_gsplat.dcp"/>
  <File Type="VDS-TIMINGSUMMARY" Name="top_gsplat_timing_summary_synth.rpt"/>
  <File Type="VDS-TIMING-PB" Name="top_gsplat_timing_summary_synth.pb"/>
  <FileSet Name="sources" Type="DesignSrcs" RelSrcDir="$PSRCDIR/sources_1">
    <Filter Type="Srcs"/>
    <File Path="$PSRCDIR/sources_1/imports/src/alpha_blender.vhd">
      <FileInfo>
        <Attr Name="ImportPath" Val="$PPRDIR/src/alpha_blender.vhd"/>
        <Attr Name="ImportTime" Val="1778574966"/>
        <Attr Name="UsedIn" Val="synthesis"/>
        <Attr Name="UsedIn" Val="simulation"/>
      </FileInfo>
    </File>
    <File Path="$PSRCDIR/sources_1/imports/src/camera_controller.vhd">
      <FileInfo>
        <Attr Name="ImportPath" Val="$PPRDIR/src/camera_controller.vhd"/>
        <Attr Name="ImportTime" Val="1779089332"/>
        <Attr Name="UsedIn" Val="synthesis"/>
        <Attr Name="UsedIn" Val="simulation"/>
      </FileInfo>
    </File>
    <File Path="$PSRCDIR/sources_1/imports/src/clk_gen.vhd">
      <FileInfo>
        <Attr Name="ImportPath" Val="$PPRDIR/src/clk_gen.vhd"/>
        <Attr Name="ImportTime" Val="1778574966"/>
        <Attr Name="UsedIn" Val="synthesis"/>
        <Attr Name="UsedIn" Val="simulation"/>
      </FileInfo>
    </File>
    <File Path="$PSRCDIR/sources_1/imports/src/framebuffer.vhd">
      <FileInfo>
        <Attr Name="ImportPath" Val="$PPRDIR/src/framebuffer.vhd"/>
        <Attr Name="ImportTime" Val="1778574966"/>
        <Attr Name="UsedIn" Val="synthesis"/>
        <Attr Name="UsedIn" Val="simulation"/>
      </FileInfo>
    </File>
    <File Path="$PSRCDIR/sources_1/imports/src/gaussian_lut.vhd">
      <FileInfo>
        <Attr Name="ImportPath" Val="$PPRDIR/src/gaussian_lut.vhd"/>
        <Attr Name="ImportTime" Val="1778574966"/>
        <Attr Name="UsedIn" Val="synthesis"/>
        <Attr Name="UsedIn" Val="simulation"/>
      </FileInfo>
    </File>
    <File Path="$PSRCDIR/sources_1/imports/src/render_controller.vhd">
      <FileInfo>
        <Attr Name="ImportPath" Val="$PPRDIR/src/render_controller.vhd"/>
        <Attr Name="ImportTime" Val="1778574966"/>
        <Attr Name="UsedIn" Val="synthesis"/>
        <Attr Name="UsedIn" Val="simulation"/>
      </FileInfo>
    </File>
    <File Path="$PSRCDIR/sources_1/imports/src/splat_rasterizer.vhd">
      <FileInfo>
        <Attr Name="ImportPath" Val="$PPRDIR/src/splat_rasterizer.vhd"/>
        <Attr Name="ImportTime" Val="1779086789"/>
        <Attr Name="UsedIn" Val="synthesis"/>
        <Attr Name="UsedIn" Val="simulation"/>
      </FileInfo>
    </File>
    <File Path="$PSRCDIR/sources_1/imports/src/splat_rom.vhd">
      <FileInfo>
        <Attr Name="ImportPath" Val="$PPRDIR/src/splat_rom.vhd"/>
        <Attr Name="ImportTime" Val="1779086762"/>
        <Attr Name="UsedIn" Val="synthesis"/>
        <Attr Name="UsedIn" Val="simulation"/>
      </FileInfo>
    </File>
    <File Path="$PSRCDIR/sources_1/imports/src/vga_timing.vhd">
      <FileInfo>
        <Attr Name="ImportPath" Val="$PPRDIR/src/vga_timing.vhd"/>
        <Attr Name="ImportTime" Val="1778574966"/>
        <Attr Name="UsedIn" Val="synthesis"/>
        <Attr Name="UsedIn" Val="simulation"/>
      </FileInfo>
    </File>
    <File Path="$PSRCDIR/sources_1/imports/src/vga_controller.vhd">
      <FileInfo>
        <Attr Name="ImportPath" Val="$PPRDIR/src/vga_controller.vhd"/>
        <Attr Name="ImportTime" Val="1778574966"/>
        <Attr Name="UsedIn" Val="synthesis"/>
        <Attr Name="UsedIn" Val="simulation"/>
      </FileInfo>
    </File>
    <File Path="$PSRCDIR/sources_1/imports/src/top_gsplat.vhd">
      <FileInfo>
        <Attr Name="ImportPath" Val="$PPRDIR/src/top_gsplat.vhd"/>
        <Attr Name="ImportTime" Val="1779093608"/>
        <Attr Name="UsedIn" Val="synthesis"/>
        <Attr Name="UsedIn" Val="simulation"/>
      </FileInfo>
    </File>
    <File Path="$PPRDIR/mem/gaussian_lut.mem">
      <FileInfo>
        <Attr Name="UsedIn" Val="synthesis"/>
        <Attr Name="UsedIn" Val="simulation"/>
      </FileInfo>
    </File>
    <File Path="$PPRDIR/mem/test_gradient.mem">
      <FileInfo>
        <Attr Name="UsedIn" Val="synthesis"/>
        <Attr Name="UsedIn" Val="simulation"/>
      </FileInfo>
    </File>
    <File Path="$PPRDIR/mem/test_overlap.mem">
      <FileInfo>
        <Attr Name="UsedIn" Val="synthesis"/>
        <Attr Name="UsedIn" Val="simulation"/>
      </FileInfo>
    </File>
    <File Path="$PPRDIR/mem/test_splats.mem">
      <FileInfo>
        <Attr Name="UsedIn" Val="synthesis"/>
        <Attr Name="UsedIn" Val="simulation"/>
      </FileInfo>
    </File>
    <File Path="$PSRCDIR/sources_1/imports/mem/my_scene.mem">
      <FileInfo>
        <Attr Name="ImportPath" Val="$PPRDIR/mem/my_scene.mem"/>
        <Attr Name="ImportTime" Val="1779082531"/>
        <Attr Name="UsedIn" Val="synthesis"/>
        <Attr Name="UsedIn" Val="simulation"/>
      </FileInfo>
    </File>
    <Config>
      <Option Name="DesignMode" Val="RTL"/>
      <Option Name="TopModule" Val="top_gsplat"/>
    </Config>
  </FileSet>
  <FileSet Name="constrs_in" Type="Constrs" RelSrcDir="$PSRCDIR/constrs_1">
    <Filter Type="Constrs"/>
    <File Path="$PPRDIR/constrs/gsplat.xdc">
      <FileInfo>
        <Attr Name="UsedIn" Val="synthesis"/>
        <Attr Name="UsedIn" Val="implementation"/>
      </FileInfo>
    </File>
    <Config>
      <Option Name="ConstrsType" Val="XDC"/>
    </Config>
  </FileSet>
  <Strategy Version="1" Minor="2">
    <StratHandle Name="Vivado Synthesis Defaults" Flow="Vivado Synthesis 2017"/>
    <Step Id="synth_design"/>
  </Strategy>
</GenRun>
